{
"type": "FeatureCollection",
"crs": { "type": "name", "properties": { "name": "urn:ogc:def:crs:OGC:1.3:CRS84" } },
"features": [
{ "type": "Feature", "properties": { "osmid": "49627021" }, "geometry": { "type": "Point", "coordinates": [ -77.480257, 37.5385876 ] } }
]
}
